Metadata-Version: 1.0
Name: quickpackage
Version: 1
Summary: Instantly create and upload python package for your python script
Home-page: https://github.com/yask123/quick-package
Author: Yask Srivastava
Author-email: yask123@gmail.com
License: MIT
Platform: UNKNOWN
